MANIFEST.in
README.rst
setup.py
collective/__init__.py
collective.microdata.core.egg-info/PKG-INFO
collective.microdata.core.egg-info/SOURCES.txt
collective.microdata.core.egg-info/dependency_links.txt
collective.microdata.core.egg-info/entry_points.txt
collective.microdata.core.egg-info/namespace_packages.txt
collective.microdata.core.egg-info/not-zip-safe
collective.microdata.core.egg-info/requires.txt
collective.microdata.core.egg-info/top_level.txt
collective/microdata/__init__.py
collective/microdata/core/__init__.py
collective/microdata/core/adapter.py
collective/microdata/core/configure.zcml
collective/microdata/core/indexer.py
collective/microdata/core/interfaces.py
collective/microdata/core/testing.py
collective/microdata/core/browser/__init__.py
collective/microdata/core/browser/configure.zcml
collective/microdata/core/browser/resources/jquery.microdata.js
collective/microdata/core/browser/resources/schemas.js
collective/microdata/core/locales/rebuildPo.sh
collective/microdata/core/profiles/default/browserlayer.xml
collective/microdata/core/profiles/default/catalog.xml
collective/microdata/core/profiles/default/metadata.xml
collective/microdata/core/profiles/javascript_tester/jsregistry.xml
collective/microdata/core/tests/__init__.py
collective/microdata/core/tests/base.py
collective/microdata/core/tests/test_microdata_support.py
docs/HISTORY.txt
docs/INSTALL.txt
docs/LICENSE.GPL
docs/LICENSE.txt