Metadata-Version: 1.1
Name: collective.microdata.core
Version: 0.1
Summary: Core package for Plone microdata support
Home-page: https://github.com/keul/collective.microdata.core
Author: keul
Author-email: luca@keul.it
License: GPL
Keywords: plone microdata schema.org html5
Platform: UNKNOWN
Classifier: Development Status :: 4 - Beta
Classifier: Framework :: Plone
Classifier: Framework :: Plone :: 4.2
Classifier: Programming Language :: Python
